mxtheme/__init__.py
mxtheme/card.py
mxtheme/drawer.html
mxtheme/footer.html
mxtheme/header.html
mxtheme/header_search.html
mxtheme/header_sourcelink.html
mxtheme/layout.html
mxtheme/localtoc.html
mxtheme/relations.html
mxtheme/search.html
mxtheme/theme.conf
mxtheme/__pycache__/__init__.cpython-37.pyc
mxtheme/__pycache__/__init__.cpython-38.pyc
mxtheme/__pycache__/card.cpython-37.pyc
mxtheme/__pycache__/card.cpython-38.pyc
mxtheme/static/fonts.css
mxtheme/static/sphinx_materialdesign_theme.css
mxtheme/static/sphinx_materialdesign_theme.css.map
mxtheme/static/sphinx_materialdesign_theme.js
mxtheme/static/sphinx_materialdesign_theme.js.map
mxtheme/static/font/Roboto/Roboto-Regular.eot
mxtheme/static/font/Roboto/Roboto-Regular.ttf
mxtheme/static/font/Roboto/Roboto-Regular.woff
mxtheme/static/font/Roboto/Roboto-Regular.woff2
mxtheme/static/fontawesome/all.css
mxtheme/static/material-design-icons-3.0.1/iconfont/MaterialIcons-Regular.eot
mxtheme/static/material-design-icons-3.0.1/iconfont/MaterialIcons-Regular.svg
mxtheme/static/material-design-icons-3.0.1/iconfont/MaterialIcons-Regular.ttf
mxtheme/static/material-design-icons-3.0.1/iconfont/MaterialIcons-Regular.woff
mxtheme/static/material-design-icons-3.0.1/iconfont/MaterialIcons-Regular.woff2
mxtheme/static/material-design-lite-1.3.0/LICENSE
mxtheme/static/material-design-lite-1.3.0/material-grid.css
mxtheme/static/material-design-lite-1.3.0/material-grid.min.css
mxtheme/static/material-design-lite-1.3.0/material.amber-blue.min.css
mxtheme/static/material-design-lite-1.3.0/material.amber-cyan.min.css
mxtheme/static/material-design-lite-1.3.0/material.amber-deep_orange.min.css
mxtheme/static/material-design-lite-1.3.0/material.amber-deep_purple.min.css
mxtheme/static/material-design-lite-1.3.0/material.amber-green.min.css
mxtheme/static/material-design-lite-1.3.0/material.amber-indigo.min.css
mxtheme/static/material-design-lite-1.3.0/material.amber-light_blue.min.css
mxtheme-0.3.15.dist-info/LICENSE
mxtheme-0.3.15.dist-info/METADATA
mxtheme-0.3.15.dist-info/WHEEL
mxtheme-0.3.15.dist-info/entry_points.txt
mxtheme-0.3.15.dist-info/top_level.txt
mxtheme-0.3.15.dist-info/RECORD
