Metadata-Version: 2.1
Name: mxtheme
Version: 0.3.15
Summary: A Sphinx theme based on Material Design, adapted from sphinx_materialdesign_theme
Home-page: https://github.com/mli/mx-theme
Author: Mu Li
Author-email: UNKNOWN
License: MIT License
Platform: UNKNOWN
